netbox_security/__init__.py
netbox_security/apps.py
netbox_security/navigation.py
netbox_security/template_content.py
netbox_security/urls.py
netbox_security/version.py
netbox_security/api/__init__.py
netbox_security/api/serializers.py
netbox_security/api/urls.py
netbox_security/api/views.py
netbox_security/api/serializers_/__init__.py
netbox_security/api/serializers_/address.py
netbox_security/api/serializers_/address_list.py
netbox_security/api/serializers_/address_set.py
netbox_security/api/serializers_/application.py
netbox_security/api/serializers_/application_item.py
netbox_security/api/serializers_/application_set.py
netbox_security/api/serializers_/firewall_filter.py
netbox_security/api/serializers_/firewall_filter_rule.py
netbox_security/api/serializers_/nat_pool.py
netbox_security/api/serializers_/nat_pool_member.py
netbox_security/api/serializers_/nat_rule.py
netbox_security/api/serializers_/nat_rule_set.py
netbox_security/api/serializers_/policer.py
netbox_security/api/serializers_/security_zone_policy.py
netbox_security/api/serializers_/securityzone.py
netbox_security/choices/__init__.py
netbox_security/choices/application_choices.py
netbox_security/choices/firewall_filter_choices.py
netbox_security/choices/nat_pool_choices.py
netbox_security/choices/nat_rule_choices.py
netbox_security/choices/policer_choices.py
netbox_security/choices/security_policy_choices.py
netbox_security/constants/__init__.py
netbox_security/constants/constants.py
netbox_security/fields/__init__.py
netbox_security/fields/choice_field.py
netbox_security/filtersets/__init__.py
netbox_security/filtersets/address.py
netbox_security/filtersets/address_list.py
netbox_security/filtersets/address_set.py
netbox_security/filtersets/application.py
netbox_security/filtersets/application_item.py
netbox_security/filtersets/application_set.py
netbox_security/filtersets/firewall_filter.py
netbox_security/filtersets/firewall_filter_rule.py
netbox_security/filtersets/nat_pool.py
netbox_security-1.4.2.dist-info/licenses/LICENSE
netbox_security-1.4.2.dist-info/METADATA
netbox_security-1.4.2.dist-info/WHEEL
netbox_security-1.4.2.dist-info/top_level.txt
netbox_security-1.4.2.dist-info/RECORD
