Metadata-Version: 2.4
Name: netbox-security
Version: 1.4.2
Summary: A Netbox plugin for tracking Security and NAT related objects
Author-email: Andy Wilson <andy@shady.org>
Project-URL: Homepage, https://github.com/andy-shady-org/netbox-security
Project-URL: Documentation, https://github.com/andy-shady-org/netbox-security/blob/main/README.md
Project-URL: Repository, https://github.com/andy-shady-org/netbox-security
Project-URL: Issues, https://github.com/andy-shady-org/netbox-security/issues
Keywords: netbox,netbox-plugin,security
Classifier: Development Status :: 5 - Production/Stable
Requires-Python: >=3.12
License-File: LICENSE
Dynamic: license-file
